pytech/datatypes/__init__.py
pytech/datatypes/enums.py
pytech/tools/__init__.py
pytech/tools/logger.py
pytech/tools/scheduler.py
pytech_tools-2.5.3.dist-info/METADATA
pytech_tools-2.5.3.dist-info/WHEEL
pytech_tools-2.5.3.dist-info/licenses/LICENCE
pytech_tools-2.5.3.dist-info/RECORD
