Metadata-Version: 2.4
Name: pytech-tools
Version: 2.5.3
Summary: PyTech Tools
Project-URL: Homepage, https://gitlab.com/pytech-srl/resources/pytech-tools
Project-URL: Bug Tracker, https://gitlab.com/pytech-srl/resources/pytech-tools/-/issues
Project-URL: Documentation, https://pytech-srl.gitlab.io/resources/pytech-tools/
Author-email: Alessandro Grandi <alessandro.grandi@pytech.it>, Martino Silvestri <martino.silvestri@pytech.it>
License-File: LICENCE
Classifier: License :: OSI Approved :: GNU Affero General Public License v3 or later (AGPLv3+)
Classifier: Operating System :: OS Independent
Classifier: Programming Language :: Python
Classifier: Programming Language :: Python :: 3
Requires-Python: >=3.6
Requires-Dist: apscheduler>=3
